{
  "page": 1,
  "results": [
    {
      "adult": false,
      "backdrop_path": "/egoyMDLqCxzjnSrWOz50uLlJWmD.jpg",
      "genre_ids": [
        28,
        878,
        35,
        10751,
        12
      ],
      "id": 675353,
      "original_language": "en",
      "original_title": "Sonic the Hedgehog 2",
      "overview": "After settling in Green Hills, Sonic is eager to prove he has what it takes to be a true hero. His test comes when Dr. Robotnik returns, this time with a new partner, Knuckles, in search for an emerald that has the power to destroy civilizations. Sonic teams up with his own sidekick, Tails, and together they embark on a globe-trotting journey to find the emerald before it falls into the wrong hands.",
      "popularity": 12295.749,
      "poster_path": "/6DrHO1jr3qVrViUO6s6kFiAGM7.jpg",
      "release_date": "2022-03-30",
      "title": "Sonic the Hedgehog 2",
      "video": false,
      "vote_average": 7.7,
      "vote_count": 1347
    },
    {
      "adult": false,
      "backdrop_path": "/aEGiJJP91HsKVTEPy1HhmN0wRLm.jpg",
      "genre_ids": [
        28,
        12
      ],
      "id": 335787,
      "original_language": "en",
      "original_title": "Uncharted",
      "overview": "A young street-smart, Nathan Drake and his wisecracking partner Victor “Sully” Sullivan embark on a dangerous pursuit of “the greatest treasure never found” while also tracking clues that may lead to Nathan’s long-lost brother.",
      "popularity": 5338.804,
      "poster_path": "/tlZpSxYuBRoVJBOpUrPdQe9FmFq.jpg",
      "release_date": "2022-02-10",
      "title": "Uncharted",
      "video": false,
      "vote_average": 7.2,
      "vote_count": 1916
    },
    {
      "adult": false,
      "backdrop_path": "/xHrp2pq73oi9D64xigPjWW1wcz1.jpg",
      "genre_ids": [
        80,
        9648,
        53
      ],
      "id": 414906,
      "original_language": "en",
      "original_title": "The Batman",
      "overview": "In his second year of fighting crime, Batman uncovers corruption in Gotham City that connects to his own family while facing a serial killer known as the Riddler.",
      "popularity": 5095.615,
      "poster_path": "/74xTEgt7R36Fpooo50r9T25onhq.jpg",
      "release_date": "2022-03-01",
      "title": "The Batman",
      "video": false,
      "vote_average": 7.8,
      "vote_count": 4550
    },
    {
      "adult": false,
      "backdrop_path": "/fEe5fe82qHzjO4yej0o79etqsWV.jpg",
      "genre_ids": [
        16,
        35,
        28,
        10751,
        80
      ],
      "id": 629542,
      "original_language": "en",
      "original_title": "The Bad Guys",
      "overview": "When the infamous Bad Guys are finally caught after years of countless heists and being the world’s most-wanted villains, Mr. Wolf brokers a deal to save them all from prison.",
      "popularity": 4730.457,
      "poster_path": "/7qop80YfuO0BwJa1uXk1DXUUEwv.jpg",
      "release_date": "2022-03-17",
      "title": "The Bad Guys",
      "video": false,
      "vote_average": 7.8,
      "vote_count": 394
    },
    {
      "adult": false,
      "backdrop_path": "/AdyJH8kDm8xT8IKTlgpEC15ny4u.jpg",
      "genre_ids": [
        14,
        28,
        12
      ],
      "id": 453395,
      "original_language": "en",
      "original_title": "Doctor Strange in the Multiverse of Madness",
      "overview": "Doctor Strange, with the help of mystical allies both old and new, traverses the mind-bending and dangerous alternate realities of the Multiverse to confront a mysterious new adversary.",
      "popularity": 4641.408,
      "poster_path": "/9Gtg2DzBhmYamXBS1hKAhiwbBKS.jpg",
      "release_date": "2022-05-04",
      "title": "Doctor Strange in the Multiverse of Madness",
      "video": false,
      "vote_average": 7.5,
      "vote_count": 1521
    },
    {
      "adult": false,
      "backdrop_path": "/iQFcwSGbZXMkeyKrxbPnwnRo5fl.jpg",
      "genre_ids": [
        28,
        12,
        878
      ],
      "id": 634649,
      "original_language": "en",
      "original_title": "Spider-Man: No Way Home",
      "overview": "Peter Parker is unmasked and no longer able to separate his normal life from the high-stakes of being a super-hero. When he asks for help from Doctor Strange the stakes become even more dangerous, forcing him to discover what it truly means to be Spider-Man.",
      "popularity": 4160.324,
      "poster_path": "/1g0dhYtq4irTY1GPXvft6k4YLjm.jpg",
      "release_date": "2021-12-15",
      "title": "Spider-Man: No Way Home",
      "video": false,
      "vote_average": 8.1,
      "vote_count": 12769
    },
    {
      "adult": false,
      "backdrop_path": "/figlwUsXXFehX3IebdjqNLV6vWk.jpg",
      "genre_ids": [
        28,
        53
      ],
      "id": 628900,
      "original_language": "en",
      "original_title": "The Contractor",
      "overview": "After being involuntarily discharged from the U.S. Special Forces, James Harper decides to support his family by joining a private contracting organization alongside his best friend and under the command of a fellow veteran. Overseas on a covert mission, Harper must evade those trying to kill him while making his way back home.",
      "popularity": 3691.191,
      "poster_path": "/rJPGPZ5soaG27MK90oKpioSiJE2.jpg",
      "release_date": "2022-03-10",
      "title": "The Contractor",
      "video": false,
      "vote_average": 6.5,
      "vote_count": 225
    },
    {
      "adult": false,
      "backdrop_path": "/fOy2Jurz9k6RnJnMUMRDAgBwru2.jpg",
      "genre_ids": [
        16,
        10751,
        35,
        14
      ],
      "id": 508947,
      "original_language": "en",
      "original_title": "Turning Red",
      "overview": "Thirteen-year-old Mei is experiencing the awkwardness of being a teenager with a twist – when she gets too excited, she transforms into a giant red panda.",
      "popularity": 3221.005,
      "poster_path": "/qsdjk9oAKSQMWs0Vt5Pyfh6O4GZ.jpg",
      "release_date": "2022-03-10",
      "title": "Turning Red",
      "video": false,
      "vote_average": 7.4,
      "vote_count": 2118
    },
    {
      "adult": false,
      "backdrop_path": "/9Ngw106BLlNJ4iVpRHlrDfaLpCV.jpg",
      "genre_ids": [
        878,
        12,
        28
      ],
      "id": 406759,
      "original_language": "en",
      "original_title": "Moonfall",
      "overview": "A mysterious force knocks the moon from its orbit around Earth and sends it hurtling on a collision course with life as we know it.",
      "popularity": 2943.532,
      "poster_path": "/odVv1sqVs0KxBXiA8bhIBlPgalx.jpg",
      "release_date": "2022-02-03",
      "title": "Moonfall",
      "video": false,
      "vote_average": 6.5,
      "vote_count": 999
    },
    {
      "adult": false,
      "backdrop_path": "/eQN31P4IEhyp6NkdccvppJnyuJ4.jpg",
      "genre_ids": [
        28,
        12,
        14,
        878
      ],
      "id": 284052,
      "original_language": "en",
      "original_title": "Doctor Strange",
      "overview": "After his career is destroyed, a brilliant but arrogant surgeon gets a new lease on life when a sorcerer takes him under her wing and trains him to defend the world against evil.",
      "popularity": 2613.258,
      "poster_path": "/uGBVj3bEbCoZbDjjl9wTxcygko1.jpg",
      "release_date": "2016-10-25",
      "title": "Doctor Strange",
      "video": false,
      "vote_average": 7.4,
      "vote_count": 18950
    },
    {
      "adult": false,
      "backdrop_path": "/dW3fQJrshh2wYDoW4HUA7ZabsN1.jpg",
      "genre_ids": [
        28,
        53,
        80
      ],
      "id": 763285,
      "original_language": "en",
      "original_title": "Ambulance",
      "overview": "Decorated veteran Will Sharp, desperate for money to cover his wife's medical bills, asks for help from his adoptive brother Danny. A charismatic career criminal, Danny instead offers him a score: the biggest bank heist in Los Angeles history: $32 million.",
      "popularity": 2542.181,
      "poster_path": "/zT5ynZ0UR6HFfWQSRf2uKtqCyWD.jpg",
      "release_date": "2022-03-16",
      "title": "Ambulance",
      "video": false,
      "vote_average": 6.9,
      "vote_count": 569
    },
    {
      "adult": false,
      "backdrop_path": "/i0zbSmiyyylh7H3Qb4jgscz46Pm.jpg",
      "genre_ids": [
        27
      ],
      "id": 893370,
      "original_language": "es",
      "original_title": "Virus-32",
      "overview": "A virus is unleashed and a chilling massacre runs through the streets of Montevideo.",
      "popularity": 2488.051,
      "poster_path": "/wZiF79hbhLK1U2Pj9bF67NAKXQR.jpg",
      "release_date": "2022-04-21",
      "title": "Virus:32",
      "video": false,
      "vote_average": 6.9,
      "vote_count": 45
    },
    {
      "adult": false,
      "backdrop_path": "/qNRkfXBdAuXk9Qs3BEDIfmbAK9w.jpg",
      "genre_ids": [
        80,
        28
      ],
      "id": 883502,
      "original_language": "en",
      "original_title": "Fortress: Sniper's Eye",
      "overview": "Weeks after the deadly assault on Fortress Camp, Robert makes a daring rescue to save Sasha, the widow of his old nemesis Balzary. But back in the camp's command bunker, it appears Sasha may have devious plans of her own. As a new attack breaks out, Robert is confronted with a familiar face he thought he'd never see again…",
      "popularity": 2186.467,
      "poster_path": "/61J34xHVVdQHbJ4MSCWQo4e727v.jpg",
      "release_date": "2022-04-29",
      "title": "Fortress: Sniper's Eye",
      "video": false,
      "vote_average": 5.8,
      "vote_count": 25
    },
    {
      "adult": false,
      "backdrop_path": "/A3bsT0m1um6tvcmlIGxBwx9eAxn.jpg",
      "genre_ids": [
        28,
        12,
        35,
        10749
      ],
      "id": 752623,
      "original_language": "en",
      "original_title": "The Lost City",
      "overview": "A reclusive romance novelist who was sure nothing could be worse than getting stuck on a book tour with her cover model, until a kidnapping attempt sweeps them both into a cutthroat jungle adventure, proving life can be so much stranger, and more romantic, than any of her paperback fictions.",
      "popularity": 2115.816,
      "poster_path": "/neMZH82Stu91d3iqvLdNQfqPPyl.jpg",
      "release_date": "2022-03-24",
      "title": "The Lost City",
      "video": false,
      "vote_average": 6.7,
      "vote_count": 523
    },
    {
      "adult": false,
      "backdrop_path": "/2n95p9isIi1LYTscTcGytlI4zYd.jpg",
      "genre_ids": [
        80,
        18,
        53
      ],
      "id": 799876,
      "original_language": "en",
      "original_title": "The Outfit",
      "overview": "Leonard is an English tailor who used to craft suits on London’s world-famous Savile Row. After a personal tragedy, he’s ended up in Chicago, operating a small tailor shop in a rough part of town where he makes beautiful clothes for the only people around who can afford them: a family of vicious gangsters.",
      "popularity": 2002.048,
      "poster_path": "/lZa5EB6PVJBT5mxhgZS5ftqdAm6.jpg",
      "release_date": "2022-02-25",
      "title": "The Outfit",
      "video": false,
      "vote_average": 7,
      "vote_count": 206
    },
    {
      "adult": false,
      "backdrop_path": "/t9hNIUFcy0tYu55IPxjxRTTdZ6X.jpg",
      "genre_ids": [
        10749,
        18
      ],
      "id": 829557,
      "original_language": "en",
      "original_title": "365 Days: This Day",
      "overview": "Laura and Massimo are back and hotter than ever. But the reunited couple's new beginning is complicated by Massimo’s family ties and a mysterious man who enters Laura’s life to win her heart and trust, at any cost.",
      "popularity": 1878.728,
      "poster_path": "/7qU0SOVcQ8BTJLodcAlulUAG16C.jpg",
      "release_date": "2022-04-27",
      "title": "365 Days: This Day",
      "video": false,
      "vote_average": 5.6,
      "vote_count": 384
    },
    {
      "adult": false,
      "backdrop_path": "/3G1Q5xF40HkUBJXxt2DQgQzKTp5.jpg",
      "genre_ids": [
        16,
        35,
        10751,
        14
      ],
      "id": 568124,
      "original_language": "en",
      "original_title": "Encanto",
      "overview": "The tale of an extraordinary family, the Madrigals, who live hidden in the mountains of Colombia, in a magical house, in a vibrant town, in a wondrous, charmed place called an Encanto. The magic of the Encanto has blessed every child in the family with a unique gift from super strength to the power to heal—every child except one, Mirabel. But when she discovers that the magic surrounding the Encanto is in danger, Mirabel decides that she, the only ordinary Madrigal, might just be her exceptional family's last hope.",
      "popularity": 1556.561,
      "poster_path": "/4j0PNHkMr5ax3IA8tjtxcmPU3QT.jpg",
      "release_date": "2021-11-24",
      "title": "Encanto",
      "video": false,
      "vote_average": 7.7,
      "vote_count": 6419
    },
    {
      "adult": false,
      "backdrop_path": "/mhEGheJmjMrebHm1UR1hdu8avTg.jpg",
      "genre_ids": [
        28,
        80,
        18
      ],
      "id": 951470,
      "original_language": "en",
      "original_title": "Silverton Siege",
      "overview": "After a failed sabotage mission, a trio of anti-apartheid freedom fighters ends up in a tense bank hostage situation. Based on a true story.",
      "popularity": 1425.297,
      "poster_path": "/5HruMN0vvl84AqD7sCDXFNO4RhP.jpg",
      "release_date": "2022-04-27",
      "title": "Silverton Siege",
      "video": false,
      "vote_average": 6.5,
      "vote_count": 54
    },
    {
      "adult": false,
      "backdrop_path": "/An1nKjXahrChfEbZ3MAE8fsiut1.jpg",
      "genre_ids": [
        27
      ],
      "id": 661791,
      "original_language": "es",
      "original_title": "La abuela",
      "overview": "A Paris model must return to Madrid where her grandmother, who raised her, has had a stroke. But spending just a few days with this relative turns into an unexpected nightmare.",
      "popularity": 1356.249,
      "poster_path": "/eIUixNvox4U4foL5Z9KbN9HXYSM.jpg",
      "release_date": "2022-01-28",
      "title": "The Grandmother",
      "video": false,
      "vote_average": 6,
      "vote_count": 155
    },
    {
      "adult": false,
      "backdrop_path": "/zGLHX92Gk96O1DJvLil7ObJTbaL.jpg",
      "genre_ids": [
        28,
        12,
        14
      ],
      "id": 338953,
      "original_language": "en",
      "original_title": "Fantastic Beasts: The Secrets of Dumbledore",
      "overview": "Professor Albus Dumbledore knows the powerful, dark wizard Gellert Grindelwald is moving to seize control of the wizarding world. Unable to stop him alone, he entrusts magizoologist Newt Scamander to lead an intrepid team of wizards and witches. They soon encounter an array of old and new beasts as they clash with Grindelwald's growing legion of followers.",
      "popularity": 1322.253,
      "poster_path": "/jrgifaYeUtTnaH7NF5Drkgjg2MB.jpg",
      "release_date": "2022-04-06",
      "title": "Fantastic Beasts: The Secrets of Dumbledore",
      "video": false,
      "vote_average": 6.8,
      "vote_count": 997
    }
  ],
  "total_pages": 33568,
  "total_results": 671352
}